limrun_api/__init__.py
limrun_api/_base_client.py
limrun_api/_client.py
limrun_api/_compat.py
limrun_api/_constants.py
limrun_api/_exceptions.py
limrun_api/_files.py
limrun_api/_models.py
limrun_api/_qs.py
limrun_api/_resource.py
limrun_api/_response.py
limrun_api/_streaming.py
limrun_api/_types.py
limrun_api/_version.py
limrun_api/pagination.py
limrun_api/py.typed
limrun_api/_utils/__init__.py
limrun_api/_utils/_compat.py
limrun_api/_utils/_datetime_parse.py
limrun_api/_utils/_logs.py
limrun_api/_utils/_proxy.py
limrun_api/_utils/_reflection.py
limrun_api/_utils/_resources_proxy.py
limrun_api/_utils/_streams.py
limrun_api/_utils/_sync.py
limrun_api/_utils/_transform.py
limrun_api/_utils/_typing.py
limrun_api/_utils/_utils.py
limrun_api/lib/.keep
limrun_api/resources/__init__.py
limrun_api/resources/android_instances.py
limrun_api/resources/assets.py
limrun_api/resources/ios_instances.py
limrun_api/types/__init__.py
limrun_api/types/android_instance.py
limrun_api/types/android_instance_create_params.py
limrun_api/types/android_instance_list_params.py
limrun_api/types/asset.py
limrun_api/types/asset_get_or_create_params.py
limrun_api/types/asset_get_or_create_response.py
limrun_api/types/asset_get_params.py
limrun_api/types/asset_list_params.py
limrun_api/types/asset_list_response.py
limrun_api/types/ios_instance.py
limrun_api/types/ios_instance_create_params.py
limrun_api/types/ios_instance_list_params.py
limrun_api-0.9.0.dist-info/METADATA
limrun_api-0.9.0.dist-info/WHEEL
limrun_api-0.9.0.dist-info/licenses/LICENSE
limrun_api-0.9.0.dist-info/RECORD
